xcherryapi/__init__.py
xcherryapi/api/__init__.py
xcherryapi/api/default_api.py
xcherryapi/api_client.py
xcherryapi/api_response.py
xcherryapi/configuration.py
xcherryapi/exceptions.py
xcherryapi/models/__init__.py
xcherryapi/models/api_error_response.py
xcherryapi/models/app_database_column_value.py
xcherryapi/models/app_database_config.py
xcherryapi/models/app_database_error.py
xcherryapi/models/app_database_error_handling.py
xcherryapi/models/app_database_read_request.py
xcherryapi/models/app_database_read_response.py
xcherryapi/models/app_database_row_read_response.py
xcherryapi/models/app_database_row_write.py
xcherryapi/models/app_database_table_config.py
xcherryapi/models/app_database_table_read_request.py
xcherryapi/models/app_database_table_read_response.py
xcherryapi/models/app_database_table_row_selector.py
xcherryapi/models/app_database_table_write.py
xcherryapi/models/app_database_write.py
xcherryapi/models/async_state_config.py
xcherryapi/models/async_state_execute_request.py
xcherryapi/models/async_state_execute_response.py
xcherryapi/models/async_state_wait_until_request.py
xcherryapi/models/async_state_wait_until_response.py
xcherryapi/models/command_request.py
xcherryapi/models/command_results.py
xcherryapi/models/command_status.py
xcherryapi/models/command_waiting_type.py
xcherryapi/models/context.py
xcherryapi/models/database_locking_type.py
xcherryapi/models/encoded_object.py
xcherryapi/models/error_sub_type.py
xcherryapi/models/key_value.py
xcherryapi/models/load_local_attributes_request.py
xcherryapi/models/load_local_attributes_response.py
xcherryapi/models/local_attribute_config.py
xcherryapi/models/local_queue_command.py
xcherryapi/models/local_queue_message.py
xcherryapi/models/local_queue_message_result.py
xcherryapi/models/local_queue_result.py
xcherryapi/models/notify_immediate_tasks_request.py
xcherryapi/models/notify_timer_tasks_request.py
xcherryapi/models/process_execution_describe_request.py
xcherryapi-0.0.3.dist-info/METADATA
xcherryapi-0.0.3.dist-info/WHEEL
xcherryapi-0.0.3.dist-info/RECORD
