Metadata-Version: 2.1
Name: xcherryapi
Version: 0.0.3
Summary: xCherry APIs
Home-page: https://github.com/xcherryio/apis
License: NoLicense
Keywords: OpenAPI,OpenAPI-Generator,xCherry APIs
Author: OpenAPI Generator Community
Author-email: team@openapitools.org
Requires-Python: >=3.7,<4.0
Classifier: License :: Other/Proprietary License
Classifier: Programming Language :: Python :: 3
Classifier: Programming Language :: Python :: 3.7
Classifier: Programming Language :: Python :: 3.8
Classifier: Programming Language :: Python :: 3.9
Classifier: Programming Language :: Python :: 3.10
Classifier: Programming Language :: Python :: 3.11
Classifier: Programming Language :: Python :: 3.12
Requires-Dist: pydantic (>=2)
Requires-Dist: python-dateutil (>=2.8.2)
Requires-Dist: typing-extensions (>=4.7.1)
Requires-Dist: urllib3 (>=1.25.3)
Project-URL: Repository, https://github.com/xcherryio/apis
